{
    "positions": [
        {"x": 60, "y": 60, "image": "images/deflated_balloon_blue.png"},
        {"x": 180, "y": 60, "image": "images/deflated_balloon_blue.png"},
        {"x": 300, "y": 60, "image": "images/deflated_balloon_blue.png"},
        {"x": 420, "y": 60, "image": "images/deflated_balloon_blue.png"},
        {"x": 60, "y": 180, "image": "images/deflated_balloon_blue.png"},
        {"x": 60, "y": 300, "image": "images/deflated_balloon_blue.png"},
        {"x": 60, "y": 420, "image": "images/deflated_balloon_blue.png"},
        {"x": 60, "y": 540, "image": "images/deflated_balloon_blue.png"},
        {"x": 420, "y": 180, "image": "images/deflated_balloon_blue.png"},
        {"x": 420, "y": 300, "image": "images/deflated_balloon_blue.png"},
        {"x": 420, "y": 420, "image": "images/deflated_balloon_blue.png"},
        {"x": 420, "y": 540, "image": "images/deflated_balloon_blue.png"}
    ]
}